graphcompress/__init__.py
graphcompress/make_subsets.py
graphcompress/maxEdgeSize.py
graphcompress/parsers.py
graphcompress/readers.py
graphcompress/builders/compress_graph.py
graphcompress/builders/index_graph.py
graph_compress-1.1.0.dist-info/LICENSE
graph_compress-1.1.0.dist-info/METADATA
graph_compress-1.1.0.dist-info/WHEEL
graph_compress-1.1.0.dist-info/top_level.txt
graph_compress-1.1.0.dist-info/RECORD
