Metadata-Version: 2.1
Name: graph-compress
Version: 1.1.0
Summary: Library designed to compress graphs
Author: TinSlim, pabtorres
Project-URL: Homepage, https://github.com/TinSlim/graph-compress
Project-URL: Issues, https://github.com/TinSlim/graph-compress/issues
Classifier: Programming Language :: Python :: 3
Classifier: License :: OSI Approved :: MIT License
Classifier: Operating System :: OS Independent
Requires-Python: >=3.9
License-File: LICENSE
